discrete_optimization/__init__.py
discrete_optimization/datasets.py
discrete_optimization/py.typed
discrete_optimization/binpack/__init__.py
discrete_optimization/binpack/parser.py
discrete_optimization/binpack/problem.py
discrete_optimization/binpack/solvers/__init__.py
discrete_optimization/binpack/solvers/cpsat.py
discrete_optimization/binpack/solvers/dp.py
discrete_optimization/binpack/solvers/greedy.py
discrete_optimization/binpack/solvers/lp.py
discrete_optimization/binpack/solvers/toulbar.py
discrete_optimization/coloring/__init__.py
discrete_optimization/coloring/parser.py
discrete_optimization/coloring/plot.py
discrete_optimization/coloring/problem.py
discrete_optimization/coloring/solvers_map.py
discrete_optimization/coloring/utils.py
discrete_optimization/coloring/minizinc/coloring.mzn
discrete_optimization/coloring/minizinc/coloring_clique.mzn
discrete_optimization/coloring/minizinc/coloring_for_lns.mzn
discrete_optimization/coloring/minizinc/coloring_subset_nodes.mzn
discrete_optimization/coloring/solvers/__init__.py
discrete_optimization/coloring/solvers/asp.py
discrete_optimization/coloring/solvers/coloring_solver.py
discrete_optimization/coloring/solvers/cp_mzn.py
discrete_optimization/coloring/solvers/cpmpy.py
discrete_optimization/coloring/solvers/cpsat.py
discrete_optimization/coloring/solvers/dp.py
discrete_optimization/coloring/solvers/greedy.py
discrete_optimization/coloring/solvers/lns_cp.py
discrete_optimization/coloring/solvers/lns_lp.py
discrete_optimization/coloring/solvers/lp.py
discrete_optimization/coloring/solvers/quantum.py
discrete_optimization/coloring/solvers/starting_solution.py
discrete_optimization/coloring/solvers/toulbar.py
discrete_optimization/facility/__init__.py
discrete_optimization/facility/parser.py
discrete_optimization/facility/problem.py
discrete_optimization/facility/solvers_map.py
discrete_optimization/facility/utils.py
discrete_optimization/facility/minizinc/facility_int.mzn
discrete_optimization-0.7.0.dist-info/licenses/LICENSE
discrete_optimization-0.7.0.dist-info/METADATA
discrete_optimization-0.7.0.dist-info/WHEEL
discrete_optimization-0.7.0.dist-info/top_level.txt
discrete_optimization-0.7.0.dist-info/RECORD
