Metadata-Version: 2.4
Name: discrete-optimization
Version: 0.7.0
Summary: Discrete optimization library
Author-email: Airbus AI Research <scikit-decide@airbus.com>
License: MIT
Project-URL: documentation, https://airbus.github.io/discrete-optimization
Project-URL: repository, https://github.com/airbus/discrete-optimization
Classifier: Intended Audience :: Science/Research
Classifier: Intended Audience :: Developers
Classifier: Development Status :: 4 - Beta
Classifier: Topic :: Software Development
Classifier: Topic :: Scientific/Engineering
Classifier: License :: OSI Approved :: MIT License
Classifier: Natural Language :: English
Classifier: Operating System :: Microsoft :: Windows
Classifier: Operating System :: POSIX
Classifier: Operating System :: Unix
Classifier: Operating System :: MacOS
Classifier: Programming Language :: Python
Classifier: Programming Language :: Python :: 3
Classifier: Programming Language :: Python :: 3.8
Classifier: Programming Language :: Python :: 3.9
Classifier: Programming Language :: Python :: 3.10
Classifier: Programming Language :: Python :: 3.11
Classifier: Programming Language :: Python :: 3.12
Classifier: Topic :: Software Development
Classifier: Topic :: Scientific/Engineering
Requires-Python: >=3.9
License-File: LICENSE
Requires-Dist: shapely>=1.7
Requires-Dist: minizinc>=0.6.0
Requires-Dist: deap>=1.3.1
Requires-Dist: networkx>=2.5
Requires-Dist: numba>=0.50
Requires-Dist: matplotlib>=3.1
Requires-Dist: seaborn>=0.10.1
Requires-Dist: pymzn>=0.18.3
Requires-Dist: ortools>=9.8
Requires-Dist: tqdm>=4.62.3
Requires-Dist: sortedcontainers>=2.4
Requires-Dist: deprecation
Requires-Dist: typing-extensions>=4.4
Requires-Dist: cpmpy>=0.9.9
Requires-Dist: scipy
Requires-Dist: numpy>=1.21
Requires-Dist: clingo>=5.6
Requires-Dist: didppy>=0.8.0
Requires-Dist: setuptools
Requires-Dist: pandas>=2
Provides-Extra: test
Requires-Dist: pytest; extra == "test"
Requires-Dist: pytest-cov; extra == "test"
Requires-Dist: scikit-learn>=1.0; extra == "test"
Requires-Dist: optuna; extra == "test"
Provides-Extra: quantum
Requires-Dist: qiskit>=1.0.2; extra == "quantum"
Requires-Dist: qiskit-algorithms>=0.3.0; extra == "quantum"
Requires-Dist: qiskit-optimization>=0.6.1; extra == "quantum"
Requires-Dist: qiskit-aer>=0.14.1; extra == "quantum"
Requires-Dist: qiskit-ibm-runtime>=0.24; extra == "quantum"
Provides-Extra: toulbar
Requires-Dist: pytoulbar2>=0.0.0.4; extra == "toulbar"
Provides-Extra: dashboard
Requires-Dist: dash; extra == "dashboard"
Requires-Dist: plotly; extra == "dashboard"
Requires-Dist: dash_bootstrap_components; extra == "dashboard"
Requires-Dist: pandas[hdf5]; extra == "dashboard"
Dynamic: license-file
